README.md
setup.py
py3whoisxm1.egg-info/PKG-INFO
py3whoisxm1.egg-info/SOURCES.txt
py3whoisxm1.egg-info/dependency_links.txt
py3whoisxm1.egg-info/not-zip-safe
py3whoisxm1.egg-info/requires.txt
py3whoisxm1.egg-info/top_level.txt
pywhoisxml/__init__.py
pywhoisxml/auth.py
pywhoisxml/conf.py
pywhoisxml/dns_lookup.py
pywhoisxml/domain_contacts.py
pywhoisxml/domain_reputation.py
pywhoisxml/email_verification.py
pywhoisxml/exceptions.py
pywhoisxml/ip_geo.py
pywhoisxml/lookup.py
pywhoisxml/screenshot.py