Metadata-Version: 2.1
Name: py3whoisxm1
Version: 1.2
Summary: A wrapper for the WhoisXML API service
Home-page: https://github.com/VarthanV/pywhoisxml
Author: Vishnu Varthan Rao
Author-email: vishnulatha006@gmail.com
License: MIT License
Keywords: pywhoisxml,whoisxml,iplookup,ip,geoip,domain reputation,website screenshot,lookup
Platform: UNKNOWN
Classifier: Intended Audience :: Developers
Classifier: License :: OSI Approved :: MIT License
Classifier: Programming Language :: Python :: 2
Classifier: Programming Language :: Python :: 2.6
Classifier: Programming Language :: Python :: 2.7
Classifier: Programming Language :: Python :: 3
Classifier: Programming Language :: Python :: 3.3
Classifier: Operating System :: OS Independent
Classifier: Topic :: Software Development :: Libraries
Classifier: Topic :: Utilities
